ancient/__init__.py
ancient/roman.py
ancient-1.0.0.dist-info/LICENSE
ancient-1.0.0.dist-info/METADATA
ancient-1.0.0.dist-info/WHEEL
ancient-1.0.0.dist-info/top_level.txt
ancient-1.0.0.dist-info/RECORD
