Metadata-Version: 2.1
Name: ancient
Version: 1.0.0
Summary: Convert between integers and Roman numerals
Home-page: https://github.com/janjoswig/Ancient
Author: Jan-Oliver Joswig
Author-email: jan.joswig@fu-berlin.de
License: UNKNOWN
Platform: UNKNOWN
Classifier: Programming Language :: Python :: 3.7
Classifier: Programming Language :: Python :: 3.8
Classifier: License :: OSI Approved :: MIT License
Classifier: Operating System :: OS Independent
Requires-Python: >=3.8
